lefse/__init__.py
lefse/lefse.py
lefse/lefse2circlader.py
lefse/lefse_format_input.py
lefse/lefse_plot_cladogram.py
lefse/lefse_plot_features.py
lefse/lefse_plot_res.py
lefse/lefse_run.py
lefse/qiime2lefse.py
lefsebiom/AbundanceTable.py
lefsebiom/CClade.py
lefsebiom/ConstantsBreadCrumbs.py
lefsebiom/ValidateData.py
lefsebiom/__init__.py
lefse-1.1.2.dist-info/METADATA
lefse-1.1.2.dist-info/WHEEL
lefse-1.1.2.dist-info/entry_points.txt
lefse-1.1.2.dist-info/top_level.txt
lefse-1.1.2.dist-info/RECORD
