Metadata-Version: 2.1
Name: lefse
Version: 1.1.2
Summary: LEfSe determines the features (organisms, clades, operational taxonomic units, genes, or functions)     most likely to explain differences between classes by coupling standard tests for statistical significance with additional tests encoding     biological consistency and effect relevance.
Home-page: http://github.com/SegataLab/lefse/
Author: Nicola Segata
Author-email: nicola.segata@unitn.it
License: UNKNOWN
Platform: UNKNOWN
Requires-Dist: numpy
Requires-Dist: matplotlib
Requires-Dist: biom-format
Requires-Dist: rpy2
